Workbook

Sheet Factura
A1: #VALUE! | D1: FACTURA DE VENTA | I1: FACTURA No.
I2: =CONCATENATE("FV-", TEXT(ROW(A1),"000")) -> FV-001
D3: FECHA DE EMISIÓN: | F3: 25/05/2025 | I3: FECHA VENCIMIENTO: | K3: =TEXT(TODAY()+30,"DD/MM/YYYY") -> 04/07/2025
A5: DATOS DEL EMISOR (PROVEEDOR)
A6: RAZÓN SOCIAL: | G6: NIT:
A7: DIRECCIÓN: | G7: CIUDAD/DEPTO:
A8: TELÉFONO: | G8: EMAIL:
A9: RÉGIMEN TRIBUTARIO: | G9: ACTIVIDAD ECONÓMICA:
A10: RESOLUCIÓN DIAN:
A11: DATOS DEL CLIENTE
A12: RAZÓN SOCIAL/NOMBRE: | G12: NIT/CC:
A13: DIRECCIÓN: | G13: CIUDAD/DEPTO:
A14: TELÉFONO: | G14: EMAIL:
A15: DETALLE DE PRODUCTOS/SERVICIOS
A16: CÓDIGO | B16: DESCRIPCIÓN | C16: CANTIDAD | D16: VALOR UNITARIO | E16: DESCUENTO (%) | F16: VALOR DESCUENTO | G16: SUBTOTAL | H16: IVA (%) | I16: VALOR IVA | J16: TOTAL
D17: =IFERROR(VLOOKUP(B17,Hoja1!$A$1:$C$18,3,FALSE),"") | F17: =IF(E17>0,D17*C17*E17/100,0) -> 0 | G17: =IF(OR(D17="",C17="",F17=""),"",IF(D17*C17-F17>=0,D17*C17-F17,"")) | I17: =IF(OR(G17="", H17=""), "", G17*H17/100) | J17: =IF(OR(G17="", I17=""), "", G17+I17)
D18: =IFERROR(VLOOKUP(B18,Hoja1!$A$1:$C$18,3,FALSE),"") | F18: =IF(E18>0,D18*C18*E18/100,0) -> 0 | G18: =IF(OR(D18="",C18="",F18=""),"",IF(D18*C18-F18>=0,D18*C18-F18,"")) | I18: =IF(OR(G18="", H18=""), "", G18*H18/100) | J18: =IF(OR(G18="", I18=""), "", G18+I18)
D19: =IFERROR(VLOOKUP(B19,Hoja1!$A$1:$C$18,3,FALSE),"") | F19: =IF(E19>0,D19*C19*E19/100,0) -> 0 | G19: =IF(OR(D19="",C19="",F19=""),"",IF(D19*C19-F19>=0,D19*C19-F19,"")) | I19: =IF(OR(G19="", H19=""), "", G19*H19/100) | J19: =IF(OR(G19="", I19=""), "", G19+I19)
D20: =IFERROR(VLOOKUP(B20,Hoja1!$A$1:$C$18,3,FALSE),"") | F20: =IF(E20>0,D20*C20*E20/100,0) -> 0 | G20: =IF(OR(D20="",C20="",F20=""),"",IF(D20*C20-F20>=0,D20*C20-F20,"")) | I20: =IF(OR(G20="", H20=""), "", G20*H20/100) | J20: =IF(OR(G20="", I20=""), "", G20+I20)
C22: 1 | D22: =IFERROR(VLOOKUP(B22,Hoja1!$A$1:$C$18,3,FALSE),"") | F22: =IF(E22>0,D22*C22*E22/100,0) -> 0 | G22: =IF(OR(D22="",C22="",F22=""),"",IF(D22*C22-F22>=0,D22*C22-F22,"")) | I22: =IF(OR(G22="", H22=""), "", G22*H22/100) | J22: =IF(OR(G22="", I22=""), "", G22+I22)
A23: 1
A24: SUBTOTAL ANTES DE IMPUESTOS: | F24: =SUM(G17:G22) -> 0
A25: TOTAL DESCUENTOS: | F25: =SUM(F17:F22) -> 0
A26: BASE GRAVABLE IVA 0%: | F26: =SUMIF(H17:H22,0,G17:G22) -> 0
A27: BASE GRAVABLE IVA 5%: | F27: =SUMIF(H17:H22,5,G17:G22) -> 0
A28: BASE GRAVABLE IVA 19%: | F28: =SUMIF(H17:H22,19,G17:G22) -> 0
A29: VALOR IVA 5%: | F29: {=IFERROR( IF(SUM(_xlfn._xlws.FILTER(I16:I21,(H16:H21=5)*(ISNUMBER(I16:I21))*(I16:I21>0)))>0, SUMPRODUCT((H16:H21=5)*(I16:I21)), "-"), "-")} -> -
A30: VALOR IVA 19%: | F30: {=IFERROR( IF(SUM(_xlfn._xlws.FILTER(I17:I22,(H17:H22=19)*(ISNUMBER(I17:I22))*(I17:I22>0)))>0, SUMPRODUCT((H17:H22=19)*(I17:I22)), "-"), "-")} -> -
A31: RETENCIÓN EN LA FUENTE: | F31: 0
A32: RETENCIÓN IVA: | F32: 0
A33: TOTAL A PAGAR: | F33: =SUM(J17:J22)-F31-F32 -> 0
A35: INFORMACIÓN ADICIONAL
A36: FORMA DE PAGO:
A37: OBSERVACIONES:
A40: CUFE: | C40: NO APLICA
A42: NO APLICA
A47: ESTA FACTURA DE VENTA ES UN TÍTULO VALOR SEGÚN EL ART. 774 DEL CÓDIGO DE COMERCIO. NO SE ACEPTAN DEVOLUCIONES DESPUÉS DE 8 DÍAS CALENDARIO DE RECIBIDA LA MERCANCÍA.

Sheet Hoja1
A1: MATERIAL/PRODUCTO | B1: CODIGO | C1: VALRO UND
A2: BANDERAS | B2: 40456 | C2: 3500
A3: CABEZAS | B3: 38477 | C3: 2600
A4: CARRITO ROJO 6X2 | B4: 76866 | C4: 45000
A5: FICHAS AMARILLAS 3X2 | B5: 66697
A6: FICHAS AMARILLAS 4X1 | B6: 37657 | C6: 24700
A7: FICHAS ROJAS 2X2 | B7: 54455 | C7: 1000
A8: FICHAS ROJAS 4X1 | B8: 56722 | C8: 25000
A9: FICHAS VERDES 2X1 | B9: 22846 | C9: 17000
A10: FICHAS VERDES 2X2 | B10: 10942 | C10: 1000
A11: FICHAS VERDES 4X1 | B11: 63215 | C11: 25000
A12: ROJO BASE | B12: 35269 | C12: 7800
A13: ROJO TECHO 3X2 | B13: 48590 | C13: 8600
A14: CARRITO AMARILLO 2X2 | B14: 22793 | C14: 3800
A15: CARRITO AMARILLO 6X2 | B15: 48320 | C15: 41000
A16: CARRITO VERDE 6X2 | B16: 32214 | C16: 42000
A17: AMARILLO BASE | B17: 9641 | C17: 7800
A18: AMARILLO TECHO 2X2 | B18: 47267 | C18: 7600
